[
{"date": "2018-09-14", "activity": "clicked", "userId": "users.test.2", "productId": "15583"},
{"date": "2018-09-14", "activity": "bought", "userId": "users.test.9", "productId": "9954"},
{"date": "2018-09-14", "activity": "bought", "userId": "users.test.0", "productId": "4035"},
{"date": "2018-09-14", "activity": "clicked", "userId": "users.test.8", "productId": "10254"},
{"date": "2018-09-14", "activity": "bought", "userId": "users.test.1", "productId": "8122"},
{"date": "2018-09-14", "activity": "bought", "userId": "users.test.7", "productId": "14766"},
{"date": "2018-09-14", "activity": "bought", "userId": "users.test.0", "productId": "4875"},
{"date": "2018-09-14", "activity": "bought", "userId": "users.test.3", "productId": "21037"},
{"date": "2018-09-14", "activity": "bought", "userId": "users.test.1", "productId": "18658"},
{"date": "2018-09-14", "activity": "clicked", "userId": "users.test.8", "productId": "13120"},
{"date": "2018-09-14", "activity": "clicked", "userId": "users.test.9", "productId": "9088"},
{"date": "2018-09-14", "activity": "clicked", "userId": "users.test.8", "productId": "3201"},
{"date": "2018-09-14", "activity": "bought", "userId": "users.test.1", "productId": "18504"},
{"date": "2018-09-14", "activity": "bought", "userId": "users.test.6", "productId": "7604"},
{"date": "2018-09-14", "activity": "bought", "userId": "users.test.6", "productId": "19379"},
{"date": "2018-09-14", "activity": "clicked", "userId": "users.test.5", "productId": "14892"},
{"date": "2018-09-14", "activity": "bought", "userId": "users.test.6", "productId": "18701"},
{"date": "2018-09-14", "activity": "clicked", "userId": "users.test.4", "productId": "16441"},
{"date": "2018-09-14", "activity": "bought", "userId": "users.test.1", "productId": "16878"},
{"date": "2018-09-14", "activity": "bought", "userId": "users.test.4", "productId": "8084"},
{"date": "2018-09-14", "activity": "bought", "userId": "users.test.1", "productId": "18549"},
{"date": "2018-09-14", "activity": "bought", "userId": "users.test.3", "productId": "14822"},
{"date": "2018-09-14", "activity": "bought", "userId": "users.test.4", "productId": "18111"},
{"date": "2018-09-14", "activity": "bought", "userId": "users.test.8", "productId": "7315"},
{"date": "2018-09-14", "activity": "bought", "userId": "users.test.9", "productId": "7538"},
{"date": "2018-09-14", "activity": "clicked", "userId": "users.test.2", "productId": "21730"},
{"date": "2018-09-14", "activity": "clicked", "userId": "users.test.7", "productId": "3897"},
{"date": "2018-09-14", "activity": "bought", "userId": "users.test.0", "productId": "12231"},
{"date": "2018-09-14", "activity": "bought", "userId": "users.test.6", "productId": "8018"},
{"date": "2018-09-14", "activity": "bought", "userId": "users.test.6", "productId": "17615"},
{"date": "2018-09-14", "activity": "clicked", "userId": "users.test.6", "productId": "4375"},
{"date": "2018-09-14", "activity": "bought", "userId": "users.test.2", "productId": "7974"},
{"date": "2018-09-14", "activity": "clicked", "userId": "users.test.8", "productId": "11019"},
{"date": "2018-09-14", "activity": "clicked", "userId": "users.test.0", "productId": "18911"},
{"date": "2018-09-14", "activity": "clicked", "userId": "users.test.7", "productId": "9602"},
{"date": "2018-09-14", "activity": "clicked", "userId": "users.test.7", "productId": "4031"},
{"date": "2018-09-14", "activity": "bought", "userId": "users.test.1", "productId": "15372"},
{"date": "2018-09-14", "activity": "bought", "userId": "users.test.9", "productId": "5234"},
{"date": "2018-09-14", "activity": "bought", "userId": "users.test.2", "productId": "10472"},
{"date": "2018-09-14", "activity": "clicked", "userId": "users.test.7", "productId": "12339"},
{"date": "2018-09-14", "activity": "clicked", "userId": "users.test.9", "productId": "10012"},
{"date": "2018-09-14", "activity": "clicked", "userId": "users.test.6", "productId": "21099"},
{"date": "2018-09-14", "activity": "clicked", "userId": "users.test.9", "productId": "4543"},
{"date": "2018-09-14", "activity": "clicked", "userId": "users.test.2", "productId": "9802"},
{"date": "2018-09-14", "activity": "clicked", "userId": "users.test.8", "productId": "4920"},
{"date": "2018-09-14", "activity": "clicked", "userId": "users.test.3", "productId": "16272"},
{"date": "2018-09-14", "activity": "clicked", "userId": "users.test.9", "productId": "15573"},
{"date": "2018-09-14", "activity": "clicked", "userId": "users.test.9", "productId": "4101"},
{"date": "2018-09-14", "activity": "clicked", "userId": "users.test.2", "productId": "3987"},
{"date": "2018-09-14", "activity": "clicked", "userId": "users.test.4", "productId": "20981"}
]